django_cache_with_mongodb/__init__.py
django_cache_with_mongodb-2024.11.27.dist-info/AUTHORS.md
django_cache_with_mongodb-2024.11.27.dist-info/LICENSE
django_cache_with_mongodb-2024.11.27.dist-info/METADATA
django_cache_with_mongodb-2024.11.27.dist-info/WHEEL
django_cache_with_mongodb-2024.11.27.dist-info/top_level.txt
django_cache_with_mongodb-2024.11.27.dist-info/RECORD
