Metadata-Version: 2.1
Name: django-cache-with-mongodb
Version: 2024.11.27
Summary: Provides caching ability through MongoDB. Forked and detached from django_mongodb_cash_backend.
Home-page: https://github.com/Olivier-OH/django-cache-with-mongodb
Author: Olivier Hoareau
Author-email: olivier.p.hoareau@gmail.com
Maintainer: Olivier Hoareau
Maintainer-email: olivier.p.hoareau@gmail.com
License: BSD-3-Clause
Keywords: django,web,cache,mongodb
Platform: OS Independent
Classifier: Development Status :: 5 - Production/Stable
Classifier: Programming Language :: Python
Classifier: Framework :: Django
Classifier: Environment :: Web Environment
Classifier: Intended Audience :: Developers
Classifier: Operating System :: OS Independent
Classifier: Programming Language :: Python
Classifier: Programming Language :: Python :: 2
Classifier: Programming Language :: Python :: 3
Classifier: Topic :: Software Development
Provides: django_cache_with_mongodb
License-File: LICENSE
License-File: AUTHORS.md
Requires-Dist: pymongo>=4.0.2
